MANIFEST.in
README.md
setup.py
./setup.py
./functioncache/__init__.py
./functioncache.egg-info/SOURCES.txt
./functioncache.egg-info/dependency_links.txt
./functioncache.egg-info/requires.txt
./functioncache.egg-info/top_level.txt
./functioncache/test/stub_for_test.py
./functioncache/test/test.py
./functioncache/test/test_filecache.py
./venv/bin/rst2html.py
./venv/bin/rst2html4.py
./venv/bin/rst2html5.py
./venv/bin/rst2latex.py
./venv/bin/rst2man.py
./venv/bin/rst2odt.py
./venv/bin/rst2odt_prepstyles.py
./venv/bin/rst2pseudoxml.py
./venv/bin/rst2s5.py
./venv/bin/rst2xetex.py
./venv/bin/rst2xml.py
./venv/bin/rstpep2html.py
./venv/lib/python3.11/site-packages/decorator.py
./venv/lib/python3.11/site-packages/py.py
./venv/lib/python3.11/site-packages/six.py
./venv/lib/python3.11/site-packages/Pygments-2.15.1.dist-info/entry_points.txt
./venv/lib/python3.11/site-packages/Pygments-2.15.1.dist-info/top_level.txt
./venv/lib/python3.11/site-packages/_distutils_hack/__init__.py
./venv/lib/python3.11/site-packages/_distutils_hack/override.py
./venv/lib/python3.11/site-packages/_pytest/__init__.py
./venv/lib/python3.11/site-packages/_pytest/_argcomplete.py
./venv/lib/python3.11/site-packages/_pytest/_version.py
./venv/lib/python3.11/site-packages/_pytest/cacheprovider.py
./venv/lib/python3.11/site-packages/_pytest/capture.py
./venv/lib/python3.11/site-packages/_pytest/compat.py
./venv/lib/python3.11/site-packages/_pytest/debugging.py
./venv/lib/python3.11/site-packages/_pytest/deprecated.py
./venv/lib/python3.11/site-packages/_pytest/doctest.py
./venv/lib/python3.11/site-packages/_pytest/faulthandler.py
./venv/lib/python3.11/site-packages/_pytest/fixtures.py
./venv/lib/python3.11/site-packages/_pytest/freeze_support.py
./venv/lib/python3.11/site-packages/_pytest/helpconfig.py
./venv/lib/python3.11/site-packages/_pytest/hookspec.py
./venv/lib/python3.11/site-packages/_pytest/junitxml.py
./venv/lib/python3.11/site-packages/_pytest/legacypath.py
./venv/lib/python3.11/site-packages/_pytest/logging.py
./venv/lib/python3.11/site-packages/_pytest/main.py
./venv/lib/python3.11/site-packages/_pytest/monkeypatch.py
./venv/lib/python3.11/site-packages/_pytest/nodes.py
./venv/lib/python3.11/site-packages/_pytest/nose.py
./venv/lib/python3.11/site-packages/_pytest/outcomes.py
./venv/lib/python3.11/site-packages/bleach-6.0.0.dist-info/top_level.txt
./venv/lib/python3.11/site-packages/bleach/_vendor/html5lib-1.1.dist-info/top_level.txt
./venv/lib/python3.11/site-packages/certifi-2023.5.7.dist-info/top_level.txt
./venv/lib/python3.11/site-packages/charset_normalizer-3.1.0.dist-info/entry_points.txt
./venv/lib/python3.11/site-packages/charset_normalizer-3.1.0.dist-info/top_level.txt
./venv/lib/python3.11/site-packages/decorator-5.1.1.dist-info/LICENSE.txt
./venv/lib/python3.11/site-packages/decorator-5.1.1.dist-info/top_level.txt
./venv/lib/python3.11/site-packages/docutils-0.20.1.dist-info/COPYING.txt
./venv/lib/python3.11/site-packages/docutils-0.20.1.dist-info/entry_points.txt
./venv/lib/python3.11/site-packages/docutils-0.20.1.dist-info/top_level.txt
./venv/lib/python3.11/site-packages/importlib_metadata-6.6.0.dist-info/top_level.txt
./venv/lib/python3.11/site-packages/jaraco.classes-3.2.3.dist-info/top_level.txt
./venv/lib/python3.11/site-packages/keyring-23.13.1.dist-info/entry_points.txt
./venv/lib/python3.11/site-packages/keyring-23.13.1.dist-info/top_level.txt
./venv/lib/python3.11/site-packages/markdown_it_py-2.2.0.dist-info/entry_points.txt
./venv/lib/python3.11/site-packages/pip-22.3.1.dist-info/LICENSE.txt
./venv/lib/python3.11/site-packages/pip-22.3.1.dist-info/entry_points.txt
./venv/lib/python3.11/site-packages/pip-22.3.1.dist-info/top_level.txt
./venv/lib/python3.11/site-packages/pkginfo-1.9.6.dist-info/LICENSE.txt
./venv/lib/python3.11/site-packages/pkginfo-1.9.6.dist-info/entry_points.txt
./venv/lib/python3.11/site-packages/pkginfo-1.9.6.dist-info/top_level.txt
./venv/lib/python3.11/site-packages/pluggy-1.0.0.dist-info/top_level.txt
./venv/lib/python3.11/site-packages/portalocker-2.7.0.dist-info/top_level.txt
./venv/lib/python3.11/site-packages/pytest-7.3.1.dist-info/entry_points.txt
./venv/lib/python3.11/site-packages/pytest-7.3.1.dist-info/top_level.txt
./venv/lib/python3.11/site-packages/readme_renderer-37.3.dist-info/top_level.txt
./venv/lib/python3.11/site-packages/requests-2.31.0.dist-info/top_level.txt
./venv/lib/python3.11/site-packages/requests_toolbelt-1.0.0.dist-info/top_level.txt
./venv/lib/python3.11/site-packages/rfc3986-2.0.0.dist-info/top_level.txt
./venv/lib/python3.11/site-packages/setuptools-65.6.3.dist-info/entry_points.txt
./venv/lib/python3.11/site-packages/setuptools-65.6.3.dist-info/top_level.txt
./venv/lib/python3.11/site-packages/six-1.16.0.dist-info/top_level.txt
./venv/lib/python3.11/site-packages/twine-4.0.2.dist-info/entry_points.txt
./venv/lib/python3.11/site-packages/twine-4.0.2.dist-info/top_level.txt
./venv/lib/python3.11/site-packages/urllib3-2.0.2.dist-info/licenses/LICENSE.txt
./venv/lib/python3.11/site-packages/webencodings-0.5.1.dist-info/top_level.txt
./venv/lib/python3.11/site-packages/zipp-3.15.0.dist-info/top_level.txt
functioncache.egg-info/PKG-INFO
functioncache.egg-info/SOURCES.txt
functioncache.egg-info/dependency_links.txt
functioncache.egg-info/requires.txt
functioncache.egg-info/top_level.txt