Metadata-Version: 2.1
Name: functioncache
Version: 0.98
Summary: Persistent caching decorator
Home-page: https://github.com/dwiel/functioncache
Author: zdwiel
Author-email: zdwiel@gmail.com
Classifier: Development Status :: 4 - Beta
Classifier: Intended Audience :: Developers
Classifier: License :: OSI Approved :: BSD License
Classifier: Operating System :: OS Independent
Classifier: Programming Language :: Python :: 2
Classifier: Programming Language :: Python :: 3
Classifier: Topic :: Utilities
Classifier: Topic :: Software Development :: Libraries :: Python Modules
